[
  {
    "_id": "56e6ad06a252ef437d59439a",
    "device": "dexcom",
    "date": 1457958105000,
    "dateString": "Mon Mar 14 08:21:45 EDT 2016",
    "sgv": 131,
    "direction": "Flat",
    "type": "sgv",
    "filtered": 162176,
    "unfiltered": 163616,
    "rssi": 172,
    "noise": 1,
    "glucose": 131
  },
  {
    "_id": "56e6abd6a252ef437d594397",
    "device": "dexcom",
    "date": 1457957806000,
    "dateString": "Mon Mar 14 08:16:46 EDT 2016",
    "sgv": 131,
    "direction": "FortyFiveUp",
    "type": "sgv",
    "filtered": 154752,
    "unfiltered": 164320,
    "rssi": 676,
    "noise": 1,
    "glucose": 131
  },
  {
    "_id": "56e6aaaba252ef437d594394",
    "device": "dexcom",
    "date": 1457957506000,
    "dateString": "Mon Mar 14 08:11:46 EDT 2016",
    "sgv": 131,
    "direction": "FortyFiveUp",
    "type": "sgv",
    "filtered": 145760,
    "unfiltered": 163744,
    "rssi": 434,
    "noise": 1,
    "glucose": 131
  },
  {
    "_id": "56e6a97ea252ef437d594391",
    "device": "dexcom",
    "date": 1457957206000,
    "dateString": "Mon Mar 14 08:06:46 EDT 2016",
    "sgv": 116,
    "direction": "FortyFiveUp",
    "type": "sgv",
    "filtered": 138176,
    "unfiltered": 149376,
    "rssi": 431,
    "noise": 1,
    "glucose": 116
  },
  {
    "_id": "56e6a852a252ef437d59438e",
    "device": "dexcom",
    "date": 1457956905000,
    "dateString": "Mon Mar 14 08:01:45 EDT 2016",
    "sgv": 110,
    "direction": "FortyFiveUp",
    "type": "sgv",
    "filtered": 133088,
    "unfiltered": 143808,
    "rssi": 194,
    "noise": 1,
    "glucose": 110
  },
  {
    "_id": "56e6a726a252ef437d59438b",
    "device": "dexcom",
    "date": 1457956605000,
    "dateString": "Mon Mar 14 07:56:45 EDT 2016",
    "sgv": 99,
    "direction": "Flat",
    "type": "sgv",
    "filtered": 130096,
    "unfiltered": 133728,
    "rssi": 170,
    "noise": 1,
    "glucose": 99
  },
  {
    "_id": "56e6a5f9a252ef437d594385",
    "device": "dexcom",
    "date": 1457956305000,
    "dateString": "Mon Mar 14 07:51:45 EDT 2016",
    "sgv": 98,
    "direction": "Flat",
    "type": "sgv",
    "filtered": 128416,
    "unfiltered": 132224,
    "rssi": 171,
    "noise": 1,
    "glucose": 98
  },
  {
    "_id": "56e6a4d1a252ef437d594382",
    "device": "dexcom",
    "date": 1457956005000,
    "dateString": "Mon Mar 14 07:46:45 EDT 2016",
    "sgv": 93,
    "direction": "Flat",
    "type": "sgv",
    "filtered": 127056,
    "unfiltered": 127984,
    "rssi": 168,
    "noise": 1,
    "glucose": 93
  },
  {
    "_id": "56e6a3a2a252ef437d59437e",
    "device": "dexcom",
    "date": 1457955706000,
    "dateString": "Mon Mar 14 07:41:46 EDT 2016",
    "sgv": 93,
    "direction": "Flat",
    "type": "sgv",
    "filtered": 126192,
    "unfiltered": 127552,
    "rssi": 421,
    "noise": 1,
    "glucose": 93
  },
  {
    "_id": "56e6a3a4a252ef437d59437f",
    "device": "dexcom",
    "type": "cal",
    "date": 1457955706000,
    "dateString": "Mon Mar 14 07:41:46 EDT 2016",
    "slope": 957.2779747666664,
    "intercept": 33850.268086268195,
    "scale": 1
  }
]
