[
  {
    "_id": "56f6ce83a252ef437d596cc1",
    "device": "dexcom",
    "date": 1459015236000,
    "dateString": "Sat Mar 26 14:00:36 EDT 2016",
    "sgv": 126,
    "direction": "FortyFiveUp",
    "type": "sgv",
    "filtered": 187488,
    "unfiltered": 203200,
    "rssi": 173,
    "noise": 1,
    "glucose": 126
  },
  {
    "_id": "56f6cd56a252ef437d596cbe",
    "device": "dexcom",
    "date": 1459014936000,
    "dateString": "Sat Mar 26 13:55:36 EDT 2016",
    "sgv": 118,
    "direction": "FortyFiveUp",
    "type": "sgv",
    "filtered": 173760,
    "unfiltered": 193792,
    "rssi": 180,
    "noise": 1,
    "glucose": 118
  },
  {
    "_id": "56f6cc2ba252ef437d596cbb",
    "device": "dexcom",
    "date": 1459014636000,
    "dateString": "Sat Mar 26 13:50:36 EDT 2016",
    "sgv": 112,
    "direction": "FortyFiveUp",
    "type": "sgv",
    "filtered": 161792,
    "unfiltered": 186464,
    "rssi": 172,
    "noise": 1,
    "glucose": 112
  },
  {
    "_id": "56f6caffa252ef437d596cb8",
    "device": "dexcom",
    "date": 1459014336000,
    "dateString": "Sat Mar 26 13:45:36 EDT 2016",
    "sgv": 97,
    "direction": "Flat",
    "type": "sgv",
    "filtered": 154688,
    "unfiltered": 168096,
    "rssi": 180,
    "noise": 1,
    "glucose": 97
  },
  {
    "_id": "56f6c9d4a252ef437d596cb5",
    "device": "dexcom",
    "date": 1459014036000,
    "dateString": "Sat Mar 26 13:40:36 EDT 2016",
    "sgv": 88,
    "direction": "Flat",
    "type": "sgv",
    "filtered": 152576,
    "unfiltered": 157376,
    "rssi": 171,
    "noise": 1,
    "glucose": 88
  },
  {
    "_id": "56f6c8a7a252ef437d596cb2",
    "device": "dexcom",
    "date": 1459013736000,
    "dateString": "Sat Mar 26 13:35:36 EDT 2016",
    "sgv": 83,
    "direction": "Flat",
    "type": "sgv",
    "filtered": 153152,
    "unfiltered": 151200,
    "rssi": 167,
    "noise": 1,
    "glucose": 83
  },
  {
    "_id": "56f6c77ba252ef437d596caf",
    "device": "dexcom",
    "date": 1459013436000,
    "dateString": "Sat Mar 26 13:30:36 EDT 2016",
    "sgv": 84,
    "direction": "Flat",
    "type": "sgv",
    "filtered": 154592,
    "unfiltered": 151808,
    "rssi": 169,
    "noise": 1,
    "glucose": 84
  },
  {
    "_id": "56f6c651a252ef437d596cac",
    "device": "dexcom",
    "date": 1459013136000,
    "dateString": "Sat Mar 26 13:25:36 EDT 2016",
    "sgv": 86,
    "direction": "Flat",
    "type": "sgv",
    "filtered": 155936,
    "unfiltered": 154720,
    "rssi": 165,
    "noise": 1,
    "glucose": 86
  },
  {
    "_id": "56f6c523a252ef437d596ca9",
    "device": "dexcom",
    "type": "cal",
    "date": 1459012838000,
    "dateString": "Sat Mar 26 13:20:38 EDT 2016",
    "slope": 1212.599645106828,
    "intercept": 44182.441622614475,
    "scale": 1
  },
  {
    "_id": "56f6c523a252ef437d596ca7",
    "device": "dexcom",
    "date": 1459012837000,
    "dateString": "Sat Mar 26 13:20:37 EDT 2016",
    "sgv": 86,
    "direction": "Flat",
    "type": "sgv",
    "filtered": 156704,
    "unfiltered": 154784,
    "rssi": 168,
    "noise": 1,
    "glucose": 86
  }
]
