[
  {
    "trend_arrow": "FLAT", 
    "system_time": "2016-02-29T09:02:52", 
    "display_time": "2016-02-29T01:01:21", 
    "glucose": 139
  }, 
  {
    "trend_arrow": "FLAT", 
    "system_time": "2016-02-29T08:57:52", 
    "display_time": "2016-02-29T00:56:21", 
    "glucose": 141
  }, 
  {
    "trend_arrow": "FLAT", 
    "system_time": "2016-02-29T08:52:53", 
    "display_time": "2016-02-29T00:51:21", 
    "glucose": 144
  }, 
  {
    "trend_arrow": "FLAT", 
    "system_time": "2016-02-29T08:47:52", 
    "display_time": "2016-02-29T00:46:21", 
    "glucose": 146
  }, 
  {
    "trend_arrow": "FLAT", 
    "system_time": "2016-02-29T08:42:53", 
    "display_time": "2016-02-29T00:41:21", 
    "glucose": 148
  }
]