[
  {
    "_id": "56f28de3a252ef437d596138",
    "device": "dexcom",
    "date": 1458736554000,
    "dateString": "Wed Mar 23 08:35:54 EDT 2016",
    "sgv": 111,
    "direction": "FortyFiveDown",
    "type": "sgv",
    "filtered": 190336,
    "unfiltered": 179936,
    "rssi": 175,
    "noise": 1,
    "glucose": 111
  },
  {
    "_id": "56f28cb7a252ef437d596135",
    "device": "dexcom",
    "date": 1458736254000,
    "dateString": "Wed Mar 23 08:30:54 EDT 2016",
    "sgv": 127,
    "direction": "NOT COMPUTABLE",
    "type": "sgv",
    "filtered": 199360,
    "unfiltered": 183872,
    "rssi": 195,
    "noise": 3,
    "glucose": 127
  },
  {
    "_id": "56f28b8ba252ef437d596132",
    "device": "dexcom",
    "date": 1458735954000,
    "dateString": "Wed Mar 23 08:25:54 EDT 2016",
    "sgv": 130,
    "direction": "NOT COMPUTABLE",
    "type": "sgv",
    "filtered": 203488,
    "unfiltered": 189024,
    "rssi": 186,
    "noise": 3,
    "glucose": 130
  },
  {
    "_id": "56f28a60a252ef437d59612f",
    "device": "dexcom",
    "date": 1458735654000,
    "dateString": "Wed Mar 23 08:20:54 EDT 2016",
    "sgv": 129,
    "direction": "Flat",
    "type": "sgv",
    "filtered": 202080,
    "unfiltered": 199200,
    "rssi": 193,
    "noise": 2,
    "glucose": 129
  },
  {
    "_id": "56f28934a252ef437d59612c",
    "device": "dexcom",
    "date": 1458735354000,
    "dateString": "Wed Mar 23 08:15:54 EDT 2016",
    "sgv": 139,
    "direction": "Flat",
    "type": "sgv",
    "filtered": 198976,
    "unfiltered": 213440,
    "rssi": 198,
    "noise": 1,
    "glucose": 139
  },
  {
    "_id": "56f28809a252ef437d596129",
    "device": "dexcom",
    "date": 1458735054000,
    "dateString": "Wed Mar 23 08:10:54 EDT 2016",
    "sgv": 129,
    "direction": "Flat",
    "type": "sgv",
    "filtered": 197856,
    "unfiltered": 201248,
    "rssi": 165,
    "noise": 1,
    "glucose": 129
  },
  {
    "_id": "56f286dca252ef437d596125",
    "device": "dexcom",
    "date": 1458734755000,
    "dateString": "Wed Mar 23 08:05:55 EDT 2016",
    "sgv": 122,
    "direction": "Flat",
    "type": "sgv",
    "filtered": 198848,
    "unfiltered": 193696,
    "rssi": 164,
    "noise": 1,
    "glucose": 122
  },
  {
    "_id": "56f286dda252ef437d596127",
    "device": "dexcom",
    "type": "cal",
    "date": 1458734755000,
    "dateString": "Wed Mar 23 08:05:55 EDT 2016",
    "slope": 1189.1513304810424,
    "intercept": 42439.69612133265,
    "scale": 1
  },
  {
    "_id": "56f286dda252ef437d596126",
    "device": "dexcom",
    "type": "mbg",
    "date": 1458734518000,
    "dateString": "Wed Mar 23 08:01:58 EDT 2016",
    "mbg": 132
  },
  {
    "_id": "56f285b2a252ef437d596122",
    "device": "dexcom",
    "date": 1458734454000,
    "dateString": "Wed Mar 23 08:00:54 EDT 2016",
    "sgv": 5,
    "direction": "NOT COMPUTABLE",
    "type": "sgv",
    "filtered": 199392,
    "unfiltered": 197696,
    "rssi": 182,
    "noise": 1,
    "glucose": 5
  }
]
