[
  {
    "_id": "56e56beda252ef437d594034",
    "device": "dexcom",
    "date": 1457875883000,
    "dateString": "Sun Mar 13 09:31:23 EDT 2016",
    "sgv": 98,
    "direction": "Flat",
    "type": "sgv",
    "filtered": 137088,
    "unfiltered": 135936,
    "rssi": 430,
    "noise": 1,
    "glucose": 98
  },
  {
    "_id": "56e56ac2a252ef437d594031",
    "device": "dexcom",
    "date": 1457875583000,
    "dateString": "Sun Mar 13 09:26:23 EDT 2016",
    "sgv": 100,
    "direction": "Flat",
    "type": "sgv",
    "filtered": 137408,
    "unfiltered": 137408,
    "rssi": 174,
    "noise": 1,
    "glucose": 100
  },
  {
    "_id": "56e56997a252ef437d59402e",
    "device": "dexcom",
    "date": 1457875284000,
    "dateString": "Sun Mar 13 09:21:24 EDT 2016",
    "sgv": 99,
    "direction": "Flat",
    "type": "sgv",
    "filtered": 137312,
    "unfiltered": 136000,
    "rssi": 680,
    "noise": 1,
    "glucose": 99
  },
  {
    "_id": "56e56869a252ef437d594029",
    "device": "dexcom",
    "date": 1457874983000,
    "dateString": "Sun Mar 13 09:16:23 EDT 2016",
    "sgv": 101,
    "direction": "Flat",
    "type": "sgv",
    "filtered": 137056,
    "unfiltered": 138112,
    "rssi": 168,
    "noise": 1,
    "glucose": 101
  },
  {
    "_id": "56e5673ea252ef437d594026",
    "device": "dexcom",
    "date": 1457874683000,
    "dateString": "Sun Mar 13 09:11:23 EDT 2016",
    "sgv": 101,
    "direction": "Flat",
    "type": "sgv",
    "filtered": 137088,
    "unfiltered": 137984,
    "rssi": 171,
    "noise": 1,
    "glucose": 101
  },
  {
    "_id": "56e56612a252ef437d594024",
    "device": "dexcom",
    "date": 1457874384000,
    "dateString": "Sun Mar 13 09:06:24 EDT 2016",
    "sgv": 100,
    "direction": "Flat",
    "type": "sgv",
    "filtered": 137344,
    "unfiltered": 137152,
    "rssi": 691,
    "noise": 1,
    "glucose": 100
  },
  {
    "_id": "56e564e8a252ef437d59401f",
    "device": "dexcom",
    "date": 1457874083000,
    "dateString": "Sun Mar 13 09:01:23 EDT 2016",
    "sgv": 98,
    "direction": "Flat",
    "type": "sgv",
    "filtered": 137248,
    "unfiltered": 135712,
    "rssi": 168,
    "noise": 1,
    "glucose": 98
  },
  {
    "_id": "56e563bea252ef437d59401c",
    "device": "dexcom",
    "date": 1457873783000,
    "dateString": "Sun Mar 13 08:56:23 EDT 2016",
    "sgv": 100,
    "direction": "Flat",
    "type": "sgv",
    "filtered": 136480,
    "unfiltered": 137632,
    "rssi": 175,
    "noise": 1,
    "glucose": 100
  },
  {
    "_id": "56e56291a252ef437d594019",
    "device": "dexcom",
    "date": 1457873483000,
    "dateString": "Sun Mar 13 08:51:23 EDT 2016",
    "sgv": 100,
    "direction": "Flat",
    "type": "sgv",
    "filtered": 135424,
    "unfiltered": 137728,
    "rssi": 169,
    "noise": 1,
    "glucose": 100
  },
  {
    "_id": "56e56164a252ef437d594016",
    "device": "dexcom",
    "date": 1457873183000,
    "dateString": "Sun Mar 13 08:46:23 EDT 2016",
    "sgv": 99,
    "direction": "Flat",
    "type": "sgv",
    "filtered": 134528,
    "unfiltered": 136480,
    "rssi": 170,
    "noise": 1,
    "glucose": 99
  }
]
