[
  {
    "trend_arrow": "FLAT", 
    "system_time": "2016-03-03T12:22:37", 
    "display_time": "2016-03-03T04:21:55", 
    "glucose": 121
  }, 
  {
    "trend_arrow": "FLAT", 
    "system_time": "2016-03-03T12:17:37", 
    "display_time": "2016-03-03T04:16:55", 
    "glucose": 121
  }, 
  {
    "trend_arrow": "FLAT", 
    "system_time": "2016-03-03T12:12:37", 
    "display_time": "2016-03-03T04:11:55", 
    "glucose": 121
  }, 
  {
    "trend_arrow": "FLAT", 
    "system_time": "2016-03-03T12:07:37", 
    "display_time": "2016-03-03T04:06:55", 
    "glucose": 118
  }, 
  {
    "trend_arrow": "FLAT", 
    "system_time": "2016-03-03T12:02:37", 
    "display_time": "2016-03-03T04:01:55", 
    "glucose": 118
  }
]