[
  {
    "_id": "56ecb8fca252ef437d595237",
    "device": "dexcom",
    "date": 1458354379000,
    "dateString": "Fri Mar 18 22:26:19 EDT 2016",
    "sgv": 100,
    "direction": "Flat",
    "type": "sgv",
    "filtered": 158240,
    "unfiltered": 157376,
    "rssi": 195,
    "noise": 1,
    "glucose": 100
  },
  {
    "_id": "56ecb7d2a252ef437d595235",
    "device": "dexcom",
    "date": 1458354079000,
    "dateString": "Fri Mar 18 22:21:19 EDT 2016",
    "sgv": 100,
    "direction": "Flat",
    "type": "sgv",
    "filtered": 158560,
    "unfiltered": 157184,
    "rssi": 181,
    "noise": 1,
    "glucose": 100
  },
  {
    "_id": "56ecb6a4a252ef437d595233",
    "device": "dexcom",
    "date": 1458353779000,
    "dateString": "Fri Mar 18 22:16:19 EDT 2016",
    "sgv": 100,
    "direction": "Flat",
    "type": "sgv",
    "filtered": 158336,
    "unfiltered": 158304,
    "rssi": 205,
    "noise": 1,
    "glucose": 100
  },
  {
    "_id": "56ecb579a252ef437d595231",
    "device": "dexcom",
    "date": 1458353479000,
    "dateString": "Fri Mar 18 22:11:19 EDT 2016",
    "sgv": 101,
    "direction": "Flat",
    "type": "sgv",
    "filtered": 157920,
    "unfiltered": 159008,
    "rssi": 206,
    "noise": 1,
    "glucose": 101
  },
  {
    "_id": "56ecb44da252ef437d59522f",
    "device": "dexcom",
    "date": 1458353179000,
    "dateString": "Fri Mar 18 22:06:19 EDT 2016",
    "sgv": 101,
    "direction": "Flat",
    "type": "sgv",
    "filtered": 157344,
    "unfiltered": 159168,
    "rssi": 202,
    "noise": 1,
    "glucose": 101
  },
  {
    "_id": "56ecb321a252ef437d59522d",
    "device": "dexcom",
    "date": 1458352879000,
    "dateString": "Fri Mar 18 22:01:19 EDT 2016",
    "sgv": 99,
    "direction": "Flat",
    "type": "sgv",
    "filtered": 155872,
    "unfiltered": 156320,
    "rssi": 203,
    "noise": 1,
    "glucose": 99
  },
  {
    "_id": "56ecb1f5a252ef437d59522a",
    "device": "dexcom",
    "date": 1458352579000,
    "dateString": "Fri Mar 18 21:56:19 EDT 2016",
    "sgv": 98,
    "direction": "Flat",
    "type": "sgv",
    "filtered": 152768,
    "unfiltered": 155840,
    "rssi": 204,
    "noise": 1,
    "glucose": 98
  },
  {
    "_id": "56ecb0caa252ef437d595227",
    "device": "dexcom",
    "date": 1458352279000,
    "dateString": "Fri Mar 18 21:51:19 EDT 2016",
    "sgv": 98,
    "direction": "Flat",
    "type": "sgv",
    "filtered": 147840,
    "unfiltered": 155712,
    "rssi": 204,
    "noise": 1,
    "glucose": 98
  },
  {
    "_id": "56ecaf9ca252ef437d595224",
    "device": "dexcom",
    "date": 1458351979000,
    "dateString": "Fri Mar 18 21:46:19 EDT 2016",
    "sgv": 94,
    "direction": "Flat",
    "type": "sgv",
    "filtered": 142432,
    "unfiltered": 150592,
    "rssi": 201,
    "noise": 1,
    "glucose": 94
  },
  {
    "_id": "56ecae70a252ef437d595221",
    "device": "dexcom",
    "date": 1458351679000,
    "dateString": "Fri Mar 18 21:41:19 EDT 2016",
    "sgv": 91,
    "direction": "Flat",
    "type": "sgv",
    "filtered": 137952,
    "unfiltered": 146784,
    "rssi": 204,
    "noise": 1,
    "glucose": 91
  }
]
