[
  {
    "_id": "56e631f7a252ef437d594242",
    "device": "dexcom",
    "date": 1457926607000,
    "dateString": "Sun Mar 13 23:36:47 EDT 2016",
    "sgv": 148,
    "direction": "Flat",
    "type": "sgv",
    "filtered": 180192,
    "unfiltered": 181184,
    "rssi": 184,
    "noise": 1,
    "glucose": 148
  },
  {
    "_id": "56e630cba252ef437d59423f",
    "device": "dexcom",
    "date": 1457926307000,
    "dateString": "Sun Mar 13 23:31:47 EDT 2016",
    "sgv": 148,
    "direction": "Flat",
    "type": "sgv",
    "filtered": 179968,
    "unfiltered": 180640,
    "rssi": 184,
    "noise": 1,
    "glucose": 148
  },
  {
    "_id": "56e62fa0a252ef437d59423c",
    "device": "dexcom",
    "date": 1457926007000,
    "dateString": "Sun Mar 13 23:26:47 EDT 2016",
    "sgv": 147,
    "direction": "Flat",
    "type": "sgv",
    "filtered": 180224,
    "unfiltered": 180128,
    "rssi": 183,
    "noise": 1,
    "glucose": 147
  },
  {
    "_id": "56e62e73a252ef437d594239",
    "device": "dexcom",
    "date": 1457925707000,
    "dateString": "Sun Mar 13 23:21:47 EDT 2016",
    "sgv": 147,
    "direction": "Flat",
    "type": "sgv",
    "filtered": 180864,
    "unfiltered": 180064,
    "rssi": 184,
    "noise": 1,
    "glucose": 147
  },
  {
    "_id": "56e62d47a252ef437d594236",
    "device": "dexcom",
    "date": 1457925407000,
    "dateString": "Sun Mar 13 23:16:47 EDT 2016",
    "sgv": 148,
    "direction": "Flat",
    "type": "sgv",
    "filtered": 181600,
    "unfiltered": 180320,
    "rssi": 184,
    "noise": 1,
    "glucose": 148
  },
  {
    "_id": "56e62c1ba252ef437d594232",
    "device": "dexcom",
    "date": 1457925107000,
    "dateString": "Sun Mar 13 23:11:47 EDT 2016",
    "sgv": 148,
    "direction": "Flat",
    "type": "sgv",
    "filtered": 181664,
    "unfiltered": 181120,
    "rssi": 184,
    "noise": 1,
    "glucose": 148
  },
  {
    "_id": "56e62aeea252ef437d59422f",
    "device": "dexcom",
    "date": 1457924807000,
    "dateString": "Sun Mar 13 23:06:47 EDT 2016",
    "sgv": 148,
    "direction": "Flat",
    "type": "sgv",
    "filtered": 180544,
    "unfiltered": 180992,
    "rssi": 184,
    "noise": 1,
    "glucose": 148
  },
  {
    "_id": "56e629c3a252ef437d59422c",
    "device": "dexcom",
    "date": 1457924507000,
    "dateString": "Sun Mar 13 23:01:47 EDT 2016",
    "sgv": 148,
    "direction": "Flat",
    "type": "sgv",
    "filtered": 178976,
    "unfiltered": 180736,
    "rssi": 183,
    "noise": 1,
    "glucose": 148
  },
  {
    "_id": "56e62897a252ef437d594229",
    "device": "dexcom",
    "date": 1457924207000,
    "dateString": "Sun Mar 13 22:56:47 EDT 2016",
    "sgv": 150,
    "direction": "Flat",
    "type": "sgv",
    "filtered": 178464,
    "unfiltered": 182880,
    "rssi": 183,
    "noise": 1,
    "glucose": 150
  },
  {
    "_id": "56e6276ca252ef437d594226",
    "device": "dexcom",
    "date": 1457923907000,
    "dateString": "Sun Mar 13 22:51:47 EDT 2016",
    "sgv": 145,
    "direction": "Flat",
    "type": "sgv",
    "filtered": 180352,
    "unfiltered": 178240,
    "rssi": 187,
    "noise": 1,
    "glucose": 145
  }
]
