[
  {
    "_id": "56eb0aeca252ef437d594e07",
    "device": "dexcom",
    "date": 1458244286000,
    "dateString": "Thu Mar 17 15:51:26 EDT 2016",
    "sgv": 172,
    "direction": "Flat",
    "type": "sgv",
    "filtered": 209280,
    "unfiltered": 207296,
    "rssi": 188,
    "noise": 1,
    "glucose": 172
  },
  {
    "_id": "56eb09bfa252ef437d594e03",
    "device": "dexcom",
    "date": 1458243986000,
    "dateString": "Thu Mar 17 15:46:26 EDT 2016",
    "sgv": 172,
    "direction": "Flat",
    "type": "sgv",
    "filtered": 211584,
    "unfiltered": 207136,
    "rssi": 192,
    "noise": 1,
    "glucose": 172
  },
  {
    "_id": "56eb0895a252ef437d594e01",
    "device": "dexcom",
    "date": 1458243686000,
    "dateString": "Thu Mar 17 15:41:26 EDT 2016",
    "sgv": 173,
    "direction": "Flat",
    "type": "sgv",
    "filtered": 212448,
    "unfiltered": 207744,
    "rssi": 192,
    "noise": 1,
    "glucose": 173
  },
  {
    "_id": "56eb0768a252ef437d594dfd",
    "device": "dexcom",
    "date": 1458243386000,
    "dateString": "Thu Mar 17 15:36:26 EDT 2016",
    "sgv": 179,
    "direction": "Flat",
    "type": "sgv",
    "filtered": 211456,
    "unfiltered": 213568,
    "rssi": 194,
    "noise": 1,
    "glucose": 179
  },
  {
    "_id": "56eb063ca252ef437d594dfa",
    "device": "dexcom",
    "date": 1458243086000,
    "dateString": "Thu Mar 17 15:31:26 EDT 2016",
    "sgv": 178,
    "direction": "Flat",
    "type": "sgv",
    "filtered": 209536,
    "unfiltered": 213376,
    "rssi": 189,
    "noise": 1,
    "glucose": 178
  },
  {
    "_id": "56eb0510a252ef437d594df8",
    "device": "dexcom",
    "date": 1458242786000,
    "dateString": "Thu Mar 17 15:26:26 EDT 2016",
    "sgv": 176,
    "direction": "Flat",
    "type": "sgv",
    "filtered": 207808,
    "unfiltered": 210624,
    "rssi": 185,
    "noise": 1,
    "glucose": 176
  },
  {
    "_id": "56eb03e6a252ef437d594df6",
    "device": "dexcom",
    "date": 1458242486000,
    "dateString": "Thu Mar 17 15:21:26 EDT 2016",
    "sgv": 174,
    "direction": "Flat",
    "type": "sgv",
    "filtered": 206432,
    "unfiltered": 208512,
    "rssi": 192,
    "noise": 1,
    "glucose": 174
  },
  {
    "_id": "56eb02b8a252ef437d594df4",
    "device": "dexcom",
    "date": 1458242186000,
    "dateString": "Thu Mar 17 15:16:26 EDT 2016",
    "sgv": 172,
    "direction": "Flat",
    "type": "sgv",
    "filtered": 205088,
    "unfiltered": 207328,
    "rssi": 191,
    "noise": 1,
    "glucose": 172
  },
  {
    "_id": "56eb0191a252ef437d594df0",
    "device": "dexcom",
    "date": 1458241886000,
    "dateString": "Thu Mar 17 15:11:26 EDT 2016",
    "sgv": 171,
    "direction": "Flat",
    "type": "sgv",
    "filtered": 203552,
    "unfiltered": 205536,
    "rssi": 187,
    "noise": 1,
    "glucose": 171
  },
  {
    "_id": "56eb006ca252ef437d594dee",
    "device": "dexcom",
    "date": 1458241586000,
    "dateString": "Thu Mar 17 15:06:26 EDT 2016",
    "sgv": 170,
    "direction": "Flat",
    "type": "sgv",
    "filtered": 201600,
    "unfiltered": 204448,
    "rssi": 184,
    "noise": 1,
    "glucose": 170
  }
]
