[
  {
    "_id": "56e9e275a252ef437d594b91",
    "device": "dexcom",
    "date": 1458168391000,
    "dateString": "Wed Mar 16 18:46:31 EDT 2016",
    "sgv": 96,
    "direction": "Flat",
    "type": "sgv",
    "filtered": 109776,
    "unfiltered": 110528,
    "rssi": 161,
    "noise": 1,
    "glucose": 96
  },
  {
    "_id": "56e9e149a252ef437d594b8f",
    "device": "dexcom",
    "date": 1458168092000,
    "dateString": "Wed Mar 16 18:41:32 EDT 2016",
    "sgv": 91,
    "direction": "FortyFiveDown",
    "type": "sgv",
    "filtered": 114256,
    "unfiltered": 106336,
    "rssi": 427,
    "noise": 1,
    "glucose": 91
  },
  {
    "_id": "56e9e01ca252ef437d594b8d",
    "device": "dexcom",
    "date": 1458167791000,
    "dateString": "Wed Mar 16 18:36:31 EDT 2016",
    "sgv": 96,
    "direction": "SingleDown",
    "type": "sgv",
    "filtered": 121344,
    "unfiltered": 110784,
    "rssi": 169,
    "noise": 1,
    "glucose": 96
  },
  {
    "_id": "56e9def0a252ef437d594b8b",
    "device": "dexcom",
    "date": 1458167491000,
    "dateString": "Wed Mar 16 18:31:31 EDT 2016",
    "sgv": 107,
    "direction": "SingleDown",
    "type": "sgv",
    "filtered": 130976,
    "unfiltered": 119584,
    "rssi": 178,
    "noise": 1,
    "glucose": 107
  },
  {
    "_id": "56e9ddc9a252ef437d594b89",
    "device": "dexcom",
    "date": 1458167191000,
    "dateString": "Wed Mar 16 18:26:31 EDT 2016",
    "sgv": 114,
    "direction": "SingleDown",
    "type": "sgv",
    "filtered": 143168,
    "unfiltered": 125040,
    "rssi": 188,
    "noise": 1,
    "glucose": 114
  },
  {
    "_id": "56e9dca0a252ef437d594b87",
    "device": "dexcom",
    "date": 1458166891000,
    "dateString": "Wed Mar 16 18:21:31 EDT 2016",
    "sgv": 127,
    "direction": "SingleDown",
    "type": "sgv",
    "filtered": 156064,
    "unfiltered": 135648,
    "rssi": 190,
    "noise": 1,
    "glucose": 127
  },
  {
    "_id": "56e9db92a252ef437d594b85",
    "device": "dexcom",
    "date": 1458166591000,
    "dateString": "Wed Mar 16 18:16:31 EDT 2016",
    "sgv": 141,
    "direction": "SingleDown",
    "type": "sgv",
    "filtered": 166624,
    "unfiltered": 147040,
    "rssi": 197,
    "noise": 1,
    "glucose": 141
  },
  {
    "_id": "56e9da64a252ef437d594b83",
    "device": "dexcom",
    "date": 1458166291000,
    "dateString": "Wed Mar 16 18:11:31 EDT 2016",
    "sgv": 159,
    "direction": "FortyFiveDown",
    "type": "sgv",
    "filtered": 172416,
    "unfiltered": 160832,
    "rssi": 199,
    "noise": 1,
    "glucose": 159
  },
  {
    "_id": "56e9d91da252ef437d594b81",
    "device": "dexcom",
    "date": 1458165991000,
    "dateString": "Wed Mar 16 18:06:31 EDT 2016",
    "sgv": 168,
    "direction": "Flat",
    "type": "sgv",
    "filtered": 173632,
    "unfiltered": 168608,
    "rssi": 199,
    "noise": 1,
    "glucose": 168
  },
  {
    "_id": "56e9d7efa252ef437d594b7f",
    "device": "dexcom",
    "date": 1458165691000,
    "dateString": "Wed Mar 16 18:01:31 EDT 2016",
    "sgv": 179,
    "direction": "Flat",
    "type": "sgv",
    "filtered": 173216,
    "unfiltered": 176800,
    "rssi": 196,
    "noise": 1,
    "glucose": 179
  }
]
