[
  {
    "_id": "56ed16baa252ef437d5952ea",
    "device": "dexcom",
    "date": 1458378377000,
    "dateString": "Sat Mar 19 05:06:17 EDT 2016",
    "sgv": 158,
    "direction": "Flat",
    "type": "sgv",
    "filtered": 229408,
    "unfiltered": 227712,
    "rssi": 206,
    "noise": 1,
    "glucose": 158
  },
  {
    "_id": "56ed1590a252ef437d5952e8",
    "device": "dexcom",
    "date": 1458378077000,
    "dateString": "Sat Mar 19 05:01:17 EDT 2016",
    "sgv": 159,
    "direction": "Flat",
    "type": "sgv",
    "filtered": 231584,
    "unfiltered": 228576,
    "rssi": 206,
    "noise": 1,
    "glucose": 159
  },
  {
    "_id": "56ed1463a252ef437d5952e6",
    "device": "dexcom",
    "date": 1458377778000,
    "dateString": "Sat Mar 19 04:56:18 EDT 2016",
    "sgv": 160,
    "direction": "Flat",
    "type": "sgv",
    "filtered": 233504,
    "unfiltered": 229344,
    "rssi": 206,
    "noise": 1,
    "glucose": 160
  },
  {
    "_id": "56ed1338a252ef437d5952e4",
    "device": "dexcom",
    "date": 1458377478000,
    "dateString": "Sat Mar 19 04:51:18 EDT 2016",
    "sgv": 162,
    "direction": "Flat",
    "type": "sgv",
    "filtered": 234880,
    "unfiltered": 232032,
    "rssi": 206,
    "noise": 1,
    "glucose": 162
  },
  {
    "_id": "56ed120da252ef437d5952e2",
    "device": "dexcom",
    "date": 1458377178000,
    "dateString": "Sat Mar 19 04:46:18 EDT 2016",
    "sgv": 164,
    "direction": "Flat",
    "type": "sgv",
    "filtered": 236544,
    "unfiltered": 235392,
    "rssi": 191,
    "noise": 1,
    "glucose": 164
  },
  {
    "_id": "56ed10e0a252ef437d5952e0",
    "device": "dexcom",
    "date": 1458376878000,
    "dateString": "Sat Mar 19 04:41:18 EDT 2016",
    "sgv": 166,
    "direction": "Flat",
    "type": "sgv",
    "filtered": 239552,
    "unfiltered": 237024,
    "rssi": 192,
    "noise": 1,
    "glucose": 166
  },
  {
    "_id": "56ed0fb4a252ef437d5952dd",
    "device": "dexcom",
    "date": 1458376578000,
    "dateString": "Sat Mar 19 04:36:18 EDT 2016",
    "sgv": 166,
    "direction": "Flat",
    "type": "sgv",
    "filtered": 243296,
    "unfiltered": 237376,
    "rssi": 193,
    "noise": 1,
    "glucose": 166
  },
  {
    "_id": "56ed0e86a252ef437d5952db",
    "device": "dexcom",
    "date": 1458376278000,
    "dateString": "Sat Mar 19 04:31:18 EDT 2016",
    "sgv": 167,
    "direction": "Flat",
    "type": "sgv",
    "filtered": 245856,
    "unfiltered": 239072,
    "rssi": 210,
    "noise": 1,
    "glucose": 167
  },
  {
    "_id": "56ed0d5ba252ef437d5952d9",
    "device": "dexcom",
    "date": 1458375978000,
    "dateString": "Sat Mar 19 04:26:18 EDT 2016",
    "sgv": 171,
    "direction": "Flat",
    "type": "sgv",
    "filtered": 245920,
    "unfiltered": 243648,
    "rssi": 208,
    "noise": 1,
    "glucose": 171
  },
  {
    "_id": "56ed0c2fa252ef437d5952d7",
    "device": "dexcom",
    "date": 1458375678000,
    "dateString": "Sat Mar 19 04:21:18 EDT 2016",
    "sgv": 175,
    "direction": "Flat",
    "type": "sgv",
    "filtered": 244288,
    "unfiltered": 248224,
    "rssi": 208,
    "noise": 1,
    "glucose": 175
  }
]
