[
  {
    "trend_arrow": "FLAT", 
    "system_time": "2016-03-02T21:32:40", 
    "display_time": "2016-03-02T13:31:57", 
    "glucose": 109
  }, 
  {
    "trend_arrow": "FLAT", 
    "system_time": "2016-03-02T21:27:40", 
    "display_time": "2016-03-02T13:26:58", 
    "glucose": 108
  }, 
  {
    "trend_arrow": "FLAT", 
    "system_time": "2016-03-02T21:22:40", 
    "display_time": "2016-03-02T13:21:58", 
    "glucose": 112
  }, 
  {
    "trend_arrow": "FLAT", 
    "system_time": "2016-03-02T21:17:40", 
    "display_time": "2016-03-02T13:16:58", 
    "glucose": 114
  }, 
  {
    "trend_arrow": "FLAT", 
    "system_time": "2016-03-02T21:12:40", 
    "display_time": "2016-03-02T13:11:58", 
    "glucose": 116
  }
]