[
  {
    "trend_arrow": "FLAT", 
    "system_time": "2016-03-02T18:02:41", 
    "display_time": "2016-03-02T10:01:58", 
    "glucose": 144
  }, 
  {
    "trend_arrow": "45_UP", 
    "system_time": "2016-03-02T17:57:41", 
    "display_time": "2016-03-02T09:56:58", 
    "glucose": 140
  }, 
  {
    "trend_arrow": "45_UP", 
    "system_time": "2016-03-02T17:52:41", 
    "display_time": "2016-03-02T09:51:58", 
    "glucose": 135
  }, 
  {
    "trend_arrow": "45_UP", 
    "system_time": "2016-03-02T17:47:41", 
    "display_time": "2016-03-02T09:46:58", 
    "glucose": 133
  }, 
  {
    "trend_arrow": "45_UP", 
    "system_time": "2016-03-02T17:42:41", 
    "display_time": "2016-03-02T09:41:58", 
    "glucose": 126
  }
]