[
  {
    "trend_arrow": "FLAT", 
    "system_time": "2016-03-02T01:42:44", 
    "display_time": "2016-03-01T17:42:01", 
    "glucose": 105
  }, 
  {
    "trend_arrow": "FLAT", 
    "system_time": "2016-03-02T01:37:44", 
    "display_time": "2016-03-01T17:37:01", 
    "glucose": 111
  }, 
  {
    "trend_arrow": "FLAT", 
    "system_time": "2016-03-02T01:32:44", 
    "display_time": "2016-03-01T17:32:01", 
    "glucose": 112
  }, 
  {
    "trend_arrow": "FLAT", 
    "system_time": "2016-03-02T01:27:44", 
    "display_time": "2016-03-01T17:27:02", 
    "glucose": 118
  }, 
  {
    "trend_arrow": "FLAT", 
    "system_time": "2016-03-02T01:22:44", 
    "display_time": "2016-03-01T17:22:01", 
    "glucose": 119
  }
]