[
  {
    "_id": "56ef5748a252ef437d595892",
    "device": "dexcom",
    "date": 1458525968000,
    "dateString": "Sun Mar 20 22:06:08 EDT 2016",
    "sgv": 154,
    "direction": "Flat",
    "type": "sgv",
    "filtered": 230656,
    "unfiltered": 234080,
    "rssi": 180,
    "noise": 1,
    "glucose": 154
  },
  {
    "_id": "56ef561ba252ef437d59588c",
    "device": "dexcom",
    "date": 1458525668000,
    "dateString": "Sun Mar 20 22:01:08 EDT 2016",
    "sgv": 152,
    "direction": "Flat",
    "type": "sgv",
    "filtered": 231968,
    "unfiltered": 232000,
    "rssi": 179,
    "noise": 1,
    "glucose": 152
  },
  {
    "_id": "56ef54f3a252ef437d595888",
    "device": "dexcom",
    "date": 1458525368000,
    "dateString": "Sun Mar 20 21:56:08 EDT 2016",
    "sgv": 146,
    "direction": "Flat",
    "type": "sgv",
    "filtered": 231776,
    "unfiltered": 224256,
    "rssi": 180,
    "noise": 1,
    "glucose": 146
  },
  {
    "_id": "56ef53cba252ef437d595884",
    "device": "dexcom",
    "date": 1458525068000,
    "dateString": "Sun Mar 20 21:51:08 EDT 2016",
    "sgv": 153,
    "direction": "Flat",
    "type": "sgv",
    "filtered": 228960,
    "unfiltered": 232480,
    "rssi": 182,
    "noise": 1,
    "glucose": 153
  },
  {
    "_id": "56ef529ba252ef437d595881",
    "device": "dexcom",
    "date": 1458524768000,
    "dateString": "Sun Mar 20 21:46:08 EDT 2016",
    "sgv": 155,
    "direction": "Flat",
    "type": "sgv",
    "filtered": 224960,
    "unfiltered": 235744,
    "rssi": 177,
    "noise": 1,
    "glucose": 155
  },
  {
    "_id": "56ef5169a252ef437d59587c",
    "device": "dexcom",
    "date": 1458524470000,
    "dateString": "Sun Mar 20 21:41:10 EDT 2016",
    "sgv": 148,
    "direction": "Flat",
    "type": "sgv",
    "filtered": 222208,
    "unfiltered": 226880,
    "rssi": 182,
    "noise": 1,
    "glucose": 148
  },
  {
    "_id": "56ef516aa252ef437d59587e",
    "device": "dexcom",
    "type": "cal",
    "date": 1458524470000,
    "dateString": "Sun Mar 20 21:41:10 EDT 2016",
    "slope": 1257.6505892098444,
    "intercept": 34301.49119525423,
    "scale": 1
  },
  {
    "_id": "56ef5169a252ef437d59587d",
    "device": "dexcom",
    "type": "mbg",
    "date": 1458524221000,
    "dateString": "Sun Mar 20 21:37:01 EDT 2016",
    "mbg": 160
  },
  {
    "_id": "56ef503ca252ef437d595876",
    "device": "dexcom",
    "date": 1458524168000,
    "dateString": "Sun Mar 20 21:36:08 EDT 2016",
    "sgv": 141,
    "direction": "Flat",
    "type": "sgv",
    "filtered": 221248,
    "unfiltered": 221760,
    "rssi": 189,
    "noise": 1,
    "glucose": 141
  },
  {
    "_id": "56ef4f10a252ef437d595874",
    "device": "dexcom",
    "date": 1458523868000,
    "dateString": "Sun Mar 20 21:31:08 EDT 2016",
    "sgv": 141,
    "direction": "Flat",
    "type": "sgv",
    "filtered": 221408,
    "unfiltered": 222464,
    "rssi": 209,
    "noise": 1,
    "glucose": 141
  }
]
