[
  {
    "_id": "56e68e8aa252ef437d594341",
    "device": "dexcom",
    "date": 1457950306000,
    "dateString": "Mon Mar 14 06:11:46 EDT 2016",
    "sgv": 95,
    "direction": "Flat",
    "type": "sgv",
    "filtered": 131808,
    "unfiltered": 130320,
    "rssi": 191,
    "noise": 1,
    "glucose": 95
  },
  {
    "_id": "56e68d60a252ef437d59433d",
    "device": "dexcom",
    "date": 1457950006000,
    "dateString": "Mon Mar 14 06:06:46 EDT 2016",
    "sgv": 94,
    "direction": "Flat",
    "type": "sgv",
    "filtered": 133536,
    "unfiltered": 129008,
    "rssi": 185,
    "noise": 1,
    "glucose": 94
  },
  {
    "_id": "56e68c34a252ef437d594339",
    "device": "dexcom",
    "date": 1457949706000,
    "dateString": "Mon Mar 14 06:01:46 EDT 2016",
    "sgv": 98,
    "direction": "Flat",
    "type": "sgv",
    "filtered": 134912,
    "unfiltered": 132896,
    "rssi": 185,
    "noise": 1,
    "glucose": 98
  },
  {
    "_id": "56e68b07a252ef437d594335",
    "device": "dexcom",
    "date": 1457949406000,
    "dateString": "Mon Mar 14 05:56:46 EDT 2016",
    "sgv": 100,
    "direction": "Flat",
    "type": "sgv",
    "filtered": 136128,
    "unfiltered": 134912,
    "rssi": 182,
    "noise": 1,
    "glucose": 100
  },
  {
    "_id": "56e689daa252ef437d594332",
    "device": "dexcom",
    "date": 1457949106000,
    "dateString": "Mon Mar 14 05:51:46 EDT 2016",
    "sgv": 101,
    "direction": "Flat",
    "type": "sgv",
    "filtered": 137664,
    "unfiltered": 135712,
    "rssi": 180,
    "noise": 1,
    "glucose": 101
  },
  {
    "_id": "56e688ada252ef437d59432f",
    "device": "dexcom",
    "date": 1457948806000,
    "dateString": "Mon Mar 14 05:46:46 EDT 2016",
    "sgv": 102,
    "direction": "Flat",
    "type": "sgv",
    "filtered": 139232,
    "unfiltered": 136736,
    "rssi": 181,
    "noise": 1,
    "glucose": 102
  },
  {
    "_id": "56e68782a252ef437d59432c",
    "device": "dexcom",
    "date": 1457948506000,
    "dateString": "Mon Mar 14 05:41:46 EDT 2016",
    "sgv": 103,
    "direction": "Flat",
    "type": "sgv",
    "filtered": 139872,
    "unfiltered": 137664,
    "rssi": 182,
    "noise": 1,
    "glucose": 103
  },
  {
    "_id": "56e68655a252ef437d594328",
    "device": "dexcom",
    "date": 1457948206000,
    "dateString": "Mon Mar 14 05:36:46 EDT 2016",
    "sgv": 104,
    "direction": "Flat",
    "type": "sgv",
    "filtered": 139168,
    "unfiltered": 138944,
    "rssi": 182,
    "noise": 1,
    "glucose": 104
  },
  {
    "_id": "56e6852ba252ef437d594325",
    "device": "dexcom",
    "date": 1457947906000,
    "dateString": "Mon Mar 14 05:31:46 EDT 2016",
    "sgv": 106,
    "direction": "Flat",
    "type": "sgv",
    "filtered": 138208,
    "unfiltered": 140128,
    "rssi": 181,
    "noise": 1,
    "glucose": 106
  },
  {
    "_id": "56e683fea252ef437d594322",
    "device": "dexcom",
    "date": 1457947606000,
    "dateString": "Mon Mar 14 05:26:46 EDT 2016",
    "sgv": 107,
    "direction": "Flat",
    "type": "sgv",
    "filtered": 138880,
    "unfiltered": 141344,
    "rssi": 181,
    "noise": 1,
    "glucose": 107
  }
]
