{
  "pump": {
    "battery": {
      "status": "normal", 
      "voltage": 1.31
    }, 
    "status": {
      "status": "normal", 
      "timestamp": "2016-03-22T23:45:00.000Z", 
      "bolusing": false, 
      "suspended": false
    }, 
    "reservoir": 56.8, 
    "clock": "2016-03-22T19:44:20-04:00"
  }, 
  "openaps": {
    "suggested": {
      "bg": 91, 
      "temp": "absolute", 
      "snoozeBG": 117, 
      "timestamp": "2016-03-22T23:45:08.000Z", 
      "reason": "Eventual BG 74<105bolus snooze: eventual BG range 74-117", 
      "eventualBG": 74, 
      "tick": -1
    }, 
    "iob": {
      "timestamp": "2016-03-22T23:45:04.000Z", 
      "activity": -0.0004107411111111117, 
      "iob": 0.43707126484755043, 
      "bolusiob": 0.7208380461511111
    }, 
    "enacted": {
      "bg": 91, 
      "temp": "absolute", 
      "snoozeBG": 100, 
      "recieved": true, 
      "reason": "Eventual BG 100<105, no temp, setting 0.3U/hr", 
      "rate": 0.275, 
      "eventualBG": 100, 
      "timestamp": "2016-03-22T23:22:12.000Z", 
      "duration": 30, 
      "tick": "+0"
    }
  }
}