{
  "pump": {
    "battery": {
      "status": "normal", 
      "voltage": 1.29
    }, 
    "status": {
      "status": "normal", 
      "timestamp": "2016-03-17T12:16:00.000Z", 
      "bolusing": false, 
      "suspended": false
    }, 
    "reservoir": 93.7, 
    "clock": "2016-03-17T08:15:06-04:00"
  }, 
  "openaps": {
    "suggested": {
      "bg": 118, 
      "temp": "absolute", 
      "snoozeBG": 120, 
      "timestamp": "2016-03-17T12:16:09.000Z", 
      "reason": "Eventual BG 87<105, but Avg. Delta 2.67 > Exp. Delta -0.6; no temp to cancel", 
      "eventualBG": 87, 
      "tick": "+2"
    }, 
    "iob": {
      "timestamp": "2016-03-17T12:16:04.000Z", 
      "activity": 0.00616169312169312, 
      "iob": 1.065169225437778, 
      "bolusiob": 0.5470657675200001
    }, 
    "enacted": {
      "requested": {
        "duration": 0, 
        "rate": 0, 
        "temp": "absolute"
      }, 
      "bg": 110, 
      "temp": "absolute", 
      "snoozeBG": 113, 
      "timestamp": "2016-03-17T12:01:18.000Z", 
      "reason": "Eventual BG 66<105-7, and temp 1.425 > basal 0.9", 
      "rate": 1.425, 
      "eventualBG": 66, 
      "recieved": false, 
      "duration": 2, 
      "tick": -7
    }
  }
}