{
  "pump": {
    "battery": {
      "status": "normal", 
      "voltage": 1.32
    }, 
    "status": {
      "status": "normal", 
      "timestamp": "2016-02-29T03:26:03.000Z", 
      "bolusing": false, 
      "suspended": false
    }, 
    "reservoir": 47, 
    "clock": "2016-02-28T22:24:25-05:00"
  }, 
  "openaps": {
    "suggested": {
      "bg": 152, 
      "temp": "absolute", 
      "snoozeBG": 142, 
      "timestamp": "2016-02-29T03:26:11.000Z", 
      "reason": "Eventual BG 142>125, adj. req. rate:1.9 to maxSafeBasal:1.4, temp 1.35 >~ req 1.4U/hr", 
      "eventualBG": 142, 
      "tick": "+2"
    }, 
    "iob": {
      "timestamp": "2016-02-29T03:26:06.000Z", 
      "activity": 0.0030740123456790124, 
      "iob": 0.4968291571126945, 
      "bolusiob": 0
    }, 
    "enacted": {
      "bg": 139, 
      "temp": "absolute", 
      "snoozeBG": 132, 
      "recieved": true, 
      "reason": "Eventual BG 132>125, temp 1.25<1.35U/hr", 
      "rate": 1.35, 
      "eventualBG": 132, 
      "timestamp": "2016-02-29T03:01:03.000Z", 
      "duration": 30, 
      "tick": "+2"
    }
  }
}